Datascrubber/__init__.py
Datascrubber/datacleaning.py
datascrubber-0.1.4.dist-info/METADATA
datascrubber-0.1.4.dist-info/WHEEL
datascrubber-0.1.4.dist-info/licenses/LICENSE
datascrubber-0.1.4.dist-info/RECORD
