Metadata-Version: 2.1
Name: Datascrubber
Version: 0.1.4
Summary: A data cleaning package and visualisation tool for data science projects
Project-URL: Homepage, https://github.com/muganga-charles
Author-email: Charles Muganga <mugangacharles5@gmail.com>
License-File: LICENSE
Classifier: License :: OSI Approved :: MIT License
Classifier: Operating System :: OS Independent
Classifier: Programming Language :: Python :: 3
Requires-Python: >=3.10
Requires-Dist: matplotlib
Requires-Dist: missingno
Requires-Dist: numpy
Requires-Dist: openpyxl
Requires-Dist: pandas
Requires-Dist: scikit-learn
Requires-Dist: scipy
Requires-Dist: seaborn
